README.md
setup.py
cvt/__init__.py
cvt/config.py
cvt/transform.py
cvt.egg-info/PKG-INFO
cvt.egg-info/SOURCES.txt
cvt.egg-info/dependency_links.txt
cvt.egg-info/requires.txt
cvt.egg-info/top_level.txt
cvt/functional/__init__.py
cvt/functional/functional_cv2.py
cvt/functional/functional_pil.py
cvt/functional/functional_tensor.py
cvt/functional/tensor.py
test/test1.py
test/test2.py
test/test3.py
test/test4.py