Metadata-Version: 1.0
Name: cvt
Version: 0.0.7
Summary: Image Transformation Package
Home-page: https://github.com/wangjie-ruc/cvt
Author: jie.wang
Author-email: jie.wang@ruc.edu.cn
License: BSD
Platform: UNKNOWN
